winput/__init__.py
winput/vk_codes.py
winput/winput.py
winput-1.5.0.dist-info/LICENSE
winput-1.5.0.dist-info/METADATA
winput-1.5.0.dist-info/WHEEL
winput-1.5.0.dist-info/top_level.txt
winput-1.5.0.dist-info/RECORD
