Metadata-Version: 2.1
Name: winput
Version: 1.5.0
Summary: Capture and send keyboard and mouse input
Home-page: https://github.com/Zuzu-Typ/winput
Author: Zuzu_Typ
Author-email: zuzu.typ@gmail.com
License: zlib/libpng license
Keywords: record send input cursor mouse keyboard keys hook hooks pyhook windows user32.dll user32
Classifier: Development Status :: 5 - Production/Stable
Classifier: Intended Audience :: Developers
Classifier: Topic :: Games/Entertainment
Classifier: Topic :: Software Development :: Libraries
Classifier: License :: OSI Approved :: zlib/libpng License
Classifier: Programming Language :: Python :: 3
Classifier: Programming Language :: Python :: 3.5
Classifier: Programming Language :: Python :: 3.6
Classifier: Programming Language :: Python :: 3.7
Classifier: Programming Language :: Python :: 3.8
Classifier: Programming Language :: Python :: 3.9
Classifier: Programming Language :: Python :: 3.10
License-File: LICENSE
